misaa/__init__.py
misaa/cli.py
misaa-2.3.0.dist-info/METADATA
misaa-2.3.0.dist-info/WHEEL
misaa-2.3.0.dist-info/entry_points.txt
misaa-2.3.0.dist-info/top_level.txt
misaa-2.3.0.dist-info/RECORD
